gtk_simple_loader/__init__.py
gtk_simple_loader/builder.py
gtk_simple_loader/py.typed
gtk_simple_loader-0.0.1.dist-info/LICENSE
gtk_simple_loader-0.0.1.dist-info/METADATA
gtk_simple_loader-0.0.1.dist-info/WHEEL
gtk_simple_loader-0.0.1.dist-info/top_level.txt
gtk_simple_loader-0.0.1.dist-info/RECORD
