Metadata-Version: 2.1
Name: gtk_simple_loader
Version: 0.0.1
Summary: Facilities to load simple GTK '.ui' files
Author-email: Lucas Vasco <lucasvascosc@gmail.com>
Project-URL: Homepage, https://github.com/LucasAVasco/gtk_simple_loader
Project-URL: Issues, https://github.com/LucasAVasco/gtk_simple_loader/issues
Classifier: Programming Language :: Python :: 3
Classifier: Operating System :: OS Independent
Classifier: License :: OSI Approved :: The Unlicense (Unlicense)
Classifier: Environment :: X11 Applications :: GTK
Requires-Python: >=3.10
License-File: LICENSE
